hypothesis_vcf/__init__.py
hypothesis_vcf/_version.py
hypothesis_vcf/strategies.py
hypothesis_vcf/utils.py
hypothesis_vcf-0.1.0.dist-info/LICENSE
hypothesis_vcf-0.1.0.dist-info/METADATA
hypothesis_vcf-0.1.0.dist-info/WHEEL
hypothesis_vcf-0.1.0.dist-info/top_level.txt
hypothesis_vcf-0.1.0.dist-info/RECORD
