Metadata-Version: 2.2
Name: hypothesis-vcf
Version: 0.1.0
Summary: Hypothesis strategy for generating VCF
Author-email: sgkit Developers <project@sgkit.dev>
License:                                  Apache License
Project-URL: repository, https://github.com/sgkit-dev/hypothesis-vcf
Classifier: Development Status :: 4 - Beta
Classifier: License :: OSI Approved :: Apache Software License
Classifier: Operating System :: POSIX
Classifier: Operating System :: POSIX :: Linux
Classifier: Operating System :: MacOS
Classifier: Operating System :: MacOS :: MacOS X
Classifier: Intended Audience :: Science/Research
Classifier: Programming Language :: Python
Classifier: Programming Language :: Python :: 3
Classifier: Programming Language :: Python :: 3.9
Classifier: Programming Language :: Python :: 3.10
Classifier: Programming Language :: Python :: 3.11
Classifier: Programming Language :: Python :: 3.12
Classifier: Topic :: Scientific/Engineering
Requires-Python: >=3.9
License-File: LICENSE
Requires-Dist: hypothesis
Provides-Extra: dev
Requires-Dist: pysam; extra == "dev"
Requires-Dist: pytest; extra == "dev"
